CHANGELOG.rst
calendarweek/__init__.py
calendarweek/calendarweek.py
calendarweek/django.py
calendarweek/util.py
calendarweek-0.6.dist-info/LICENSE
calendarweek-0.6.dist-info/METADATA
calendarweek-0.6.dist-info/WHEEL
calendarweek-0.6.dist-info/RECORD
