Metadata-Version: 2.1
Name: calendarweek
Version: 0.6
Summary: Utilities for working with calendar weeks in Python and Django
Home-page: https://edugit.org/AlekSIS/libs/python-calendarweek
License: Apache-2.0
Author: Dominik George
Author-email: nik@naturalnet.de
Requires-Python: >=3.10,<4.0
Classifier: Development Status :: 4 - Beta
Classifier: Framework :: Django
Classifier: Intended Audience :: Developers
Classifier: License :: OSI Approved :: Apache Software License
Classifier: Programming Language :: Python :: 3
Classifier: Programming Language :: Python :: 3.10
Classifier: Programming Language :: Python :: 3.11
Classifier: Topic :: Software Development :: Libraries :: Python Modules
Classifier: Topic :: Software Development :: Localization
Classifier: Typing :: Typed
Provides-Extra: django
Requires-Dist: Django (>=4.2,<6.0) ; extra == "django"
Project-URL: Documentation, https://edugit.org/AlekSIS/libs/python-calendarweek
Project-URL: Repository, https://edugit.org/AlekSIS/libs/python-calendarweek
